authz/__init__.py
authz/exceptions.py
authz/middleware.py
authz/utils.py
casbin_graphql_authz-1.5.0.dist-info/licenses/LICENSE
tests/__init__.py
tests/test_graphql_authz.py
casbin_graphql_authz-1.5.0.dist-info/METADATA
casbin_graphql_authz-1.5.0.dist-info/WHEEL
casbin_graphql_authz-1.5.0.dist-info/top_level.txt
casbin_graphql_authz-1.5.0.dist-info/RECORD
