Metadata-Version: 2.4
Name: casbin-graphql-authz
Version: 1.5.0
Summary: graphql-authz is an casbin authorization middleware for GraphQL
Home-page: https://github.com/officialpycasbin/graphql-authz
Author: Ezequiel Grondona
Author-email: ezequiel.grondona@gmail.com
License: Apache 2.0
Keywords: casbin,GraphQL,GraphQL middleware,rbac,access control,abac,acl,permission
Classifier: Programming Language :: Python :: 3.9
Classifier: Programming Language :: Python :: 3.10
Classifier: Programming Language :: Python :: 3.11
Classifier: Programming Language :: Python :: 3.12
Classifier: License :: OSI Approved :: Apache Software License
Classifier: Operating System :: OS Independent
Requires-Python: >=3.6
License-File: LICENSE
Requires-Dist: graphql-core
Dynamic: author
Dynamic: author-email
Dynamic: classifier
Dynamic: description
Dynamic: description-content-type
Dynamic: home-page
Dynamic: keywords
Dynamic: license
Dynamic: license-file
Dynamic: requires-dist
Dynamic: requires-python
Dynamic: summary
